setup.py
mc_bin_client/__init__.py
mc_bin_client/mc_bin_client.py
mc_bin_client/memcacheConstants.py
mc_bin_client.egg-info/PKG-INFO
mc_bin_client.egg-info/SOURCES.txt
mc_bin_client.egg-info/dependency_links.txt
mc_bin_client.egg-info/top_level.txt