Metadata-Version: 1.0
Name: mc-bin-client
Version: 1.0
Summary: Binary memcached client
Home-page: UNKNOWN
Author: Dustin Sallings
Author-email: dustin@spy.net
License: UNKNOWN
Platform: UNKNOWN
